jaxtpu/__init__.py
jaxtpu-0.1.1.dist-info/LICENSE
jaxtpu-0.1.1.dist-info/WHEEL
jaxtpu-0.1.1.dist-info/METADATA
jaxtpu-0.1.1.dist-info/RECORD
