Metadata-Version: 2.1
Name: jaxtpu
Version: 0.1.1
Summary: A helper package to install the latest JAX on TPUs, along with all necessary dependencies (e.g. libtpu-nightly)
Home-page: https://github.com/shawwn/jaxtpu
License: MIT
Author: Shawn Presser
Requires-Python: >=3.7,<4.0
Classifier: License :: OSI Approved :: MIT License
Classifier: Programming Language :: Python :: 3
Classifier: Programming Language :: Python :: 3.7
Classifier: Programming Language :: Python :: 3.8
Classifier: Programming Language :: Python :: 3.9
Requires-Dist: jax (>=0.2.18,<0.3.0)
Requires-Dist: jaxlib (==0.1.69)
Requires-Dist: libtpu-nightly (>=0.1.dev20210709,<0.2)
Project-URL: @theshawwn on Twitter, https://www.twitter.com/theshawwn
Project-URL: Shawn's Website, https://www.shawwn.com
Project-URL: Support me on Patreon, https://www.patreon.com/shawwn
Project-URL: sillysaurusx on Hacker News, https://news.ycombinator.com/threads?id=sillysaurusx
